[{"idx": 14, "type": "table", "classification": ["Property"], "content": "<table-wrap id=\"tbl1\" orientation=\"portrait\" position=\"float\">\n<label>1</label>\n<caption>\n<title>Effect of HOOC-TEMPO or TEMPO on the\nSelective Aerobic Oxidation of Methyl Phenyl Sulfide Powered by 660\nnm Red Light over PCN-222<xref ref-type=\"table-fn\" rid=\"t1fn1\"></xref>\n</title>\n</caption>\n<graphic content-type=\"header\" id=\"GRAPHIC-d14e528-autogenerated\" orientation=\"portrait\" position=\"float\" xlink:href=\"cs2c02519_0011.eps\" xlink:type=\"simple\"></graphic>\n<oasis:table colsep=\"0\" rowsep=\"0\">\n<oasis:tgroup cols=\"4\">\n<oasis:colspec align=\"left\" colname=\"col1\"></oasis:colspec>\n<oasis:colspec align=\"left\" colname=\"col2\"></oasis:colspec>\n<oasis:colspec align=\"char\" char=\".\" colname=\"col3\"></oasis:colspec>\n<oasis:colspec align=\"char\" char=\".\" colname=\"col4\"></oasis:colspec>\n<oasis:thead>\n<oasis:row>\n<oasis:entry align=\"center\">Entry</oasis:entry>\n<oasis:entry align=\"center\">TEMPO</oasis:entry>\n<oasis:entry align=\"center\">Conv. (%)<xref ref-type=\"table-fn\" rid=\"t1fn2\"></xref>\n</oasis:entry>\n<oasis:entry align=\"center\">Sel. (%)<xref ref-type=\"table-fn\" rid=\"t1fn2\"></xref>\n</oasis:entry>\n</oasis:row>\n</oasis:thead>\n<oasis:tbody>\n<oasis:row>\n<oasis:entry>\n<bold>1</bold>\n</oasis:entry>\n<oasis:entry>--</oasis:entry>\n<oasis:entry>53</oasis:entry>\n<oasis:entry>98</oasis:entry>\n</oasis:row>\n<oasis:row>\n<oasis:entry>\n<bold>2</bold>\n</oasis:entry>\n<oasis:entry>TEMPO</oasis:entry>\n<oasis:entry>62</oasis:entry>\n<oasis:entry>98</oasis:entry>\n</oasis:row>\n<oasis:row>\n<oasis:entry>\n<bold>3</bold>\n</oasis:entry>\n<oasis:entry>HOOC-TEMPO</oasis:entry>\n<oasis:entry>85</oasis:entry>\n<oasis:entry>98</oasis:entry>\n</oasis:row>\n</oasis:tbody>\n</oasis:tgroup>\n</oasis:table>\n<table-wrap-foot>\n<fn id=\"t1fn1\">\n<label>a</label>\n<p>Reaction conditions: PCN-222 (5\nmg), CH<sub>3</sub>OH (1 mL), HOOC-TEMPO (9 \u03bcmol), sulfide (0.3\nmmol), red LEDs (660 \u00b1 8 nm), air (1 atm), 15 min.</p>\n</fn>\n<fn id=\"t1fn2\">\n<label>b</label>\n<p>Determined using a gas chromatograph\u2013flame\nionization detector (GC\u2013FID) using bromobenzene as the internal\nstandard, conversion of methyl phenyl sulfide, selectivity of methyl\nphenyl sulfoxide.</p>\n</fn>\n</table-wrap-foot>\n</table-wrap>", "clean_text": "Table 1. Effect of HOOC-TEMPO or TEMPO on the Selective Aerobic Oxidation of Methyl Phenyl Sulfide Powered by 660 nm Red Light over PCN-222[^a]\n\n| Entry | TEMPO     | Conv. (%)[^b] | Sel. (%)[^b] |\n|-------|-----------|--------------|--------------|\n| 1     | --        | 53           | 98           |\n| 2     | TEMPO     | 62           | 98           |\n| 3     | HOOC-TEMPO| 85           | 98           |\n\n[^a]: Reaction conditions: PCN-222 (5 mg), CH3OH (1 mL), HOOC-TEMPO (9 \u03bcmol), sulfide (0.3 mmol), red LEDs (660 \u00b1 8 nm), air (1 atm), 15 min.\n[^b]: Determined using a gas chromatograph\u2013flame ionization detector (GC\u2013FID) using bromobenzene as the internal standard, conversion of methyl phenyl sulfide, selectivity of methyl phenyl sulfoxide.", "data": [{"meta": {"name": "", "symbol": "1", "chemical formula": ""}, "selectivity": [{"value": "98", "unit": "%", "substrate": "methyl phenyl sulfide", "catalyst": "", "pressure": "", "temperature": "", "solvent": "CH3OH", "time": "15 min"}], "conversion": [{"value": "53", "unit": "%", "substrate": "methyl phenyl sulfide", "catalyst": "", "pressure": "", "temperature": "", "solvent": "CH3OH", "time": "15 min"}]}, {"meta": {"name": "", "symbol": "2", "chemical formula": ""}, "selectivity": [{"value": "98", "unit": "%", "substrate": "methyl phenyl sulfide", "catalyst": "TEMPO", "pressure": "", "temperature": "", "solvent": "CH3OH", "time": "15 min"}], "conversion": [{"value": "62", "unit": "%", "substrate": "methyl phenyl sulfide", "catalyst": "TEMPO", "pressure": "", "temperature": "", "solvent": "CH3OH", "time": "15 min"}]}, {"meta": {"name": "", "symbol": "3", "chemical formula": ""}, "selectivity": [{"value": "98", "unit": "%", "substrate": "methyl phenyl sulfide", "catalyst": "HOOC-TEMPO", "pressure": "", "temperature": "", "solvent": "CH3OH", "time": "15 min"}], "conversion": [{"value": "85", "unit": "%", "substrate": "methyl phenyl sulfide", "catalyst": "HOOC-TEMPO", "pressure": "", "temperature": "", "solvent": "CH3OH", "time": "15 min"}]}], "include_properties": ["conversion", "selectivity"]}]