[{"idx": 7, "type": "table", "classification": ["Property"], "content": "<table border=\"0\" class=\"tgroup rtable\"><div class=\"table_caption\"><b>Table 1</b> <span id=\"tab1\">Proton conductivity at different temperatures between 80 and 140 \u00b0C and Arrhenius activation energies <span class=\"italic\">E</span><small><sub>A</sub></small> of Ni-CAU-29 at different relative humidities (%rh) of 50, 75 and 90%</span>\n</div><colgroup><col/><col/><col/><col/><col/></colgroup>\n<thead align=\"left\">\n<tr align=\"left\" valign=\"bottom\">\n<th align=\"left\" class=\"border_black\" valign=\"bottom\">Relative humidity [%rh]</th>\n<th align=\"left\" valign=\"bottom\">\n</th>\n<th align=\"left\" class=\"border_black\" valign=\"bottom\">50</th>\n<th align=\"left\" class=\"border_black\" valign=\"bottom\">75</th>\n<th align=\"left\" class=\"border_black\" valign=\"bottom\">90</th>\n</tr>\n</thead>\n<tbody align=\"left\">\n<tr align=\"left\">\n<td valign=\"top\">Conductivity [S cm<small><sup>\u22121</sup></small>]</td>\n<td valign=\"top\">\n<span>80 \u00b0C</span>\n<p class=\"otherpara\">100 \u00b0C</p>\n<p class=\"otherpara\">120 \u00b0C</p>\n<p class=\"otherpara\">140 \u00b0C</p>\n</td>\n<td valign=\"top\">\n<span>2.41 \u00d7 10<small><sup>\u22127</sup></small></span>\n<p class=\"otherpara\">3.46 \u00d7 10<small><sup>\u22127</sup></small></p>\n<p class=\"otherpara\">6.02 \u00d7 10<small><sup>\u22127</sup></small></p>\n<p class=\"otherpara\">1.04 \u00d7 10<small><sup>\u22126</sup></small></p>\n</td>\n<td valign=\"top\">\n<span>1.35 \u00d7 10<small><sup>\u22126</sup></small></span>\n<p class=\"otherpara\">1.78 \u00d7 10<small><sup>\u22126</sup></small></p>\n<p class=\"otherpara\">2.60 \u00d7 10<small><sup>\u22126</sup></small></p>\n<p class=\"otherpara\">3.42 \u00d7 10<small><sup>\u22126</sup></small></p>\n</td>\n<td valign=\"top\">\n<span>5.62 \u00d7 10<small><sup>\u22126</sup></small></span>\n<p class=\"otherpara\">5.80 \u00d7 10<small><sup>\u22126</sup></small></p>\n<p class=\"otherpara\">6.85 \u00d7 10<small><sup>\u22126</sup></small></p>\n<p class=\"otherpara\">7.82 \u00d7 10<small><sup>\u22126</sup></small></p>\n</td>\n</tr>\n<tr align=\"left\">\n<td valign=\"top\">\n<span class=\"italic\">E</span>\n<small><sub>A</sub></small> [eV]</td>\n<td valign=\"top\">\n</td>\n<td valign=\"top\">0.34</td>\n<td valign=\"top\">0.23</td>\n<td valign=\"top\">0.10</td>\n</tr>\n</tbody>\n</table>", "clean_text": "Table 1. Proton conductivity at different temperatures between 80 and 140 \u00b0C and Arrhenius activation energies *E*<sub>A</sub> of Ni-CAU-29 at different relative humidities (%rh) of 50, 75 and 90%\n\n| Relative humidity [%rh] |  | 50 | 75 | 90 |\n|-------------------------|---|----|----|----|\n| Conductivity [S cm<sup>\u22121</sup>] | 80 \u00b0C | 2.41 \u00d7 10<sup>\u22127</sup> | 1.35 \u00d7 10<sup>\u22126</sup> | 5.62 \u00d7 10<sup>\u22126</sup> |\n|  | 100 \u00b0C | 3.46 \u00d7 10<sup>\u22127</sup> | 1.78 \u00d7 10<sup>\u22126</sup> | 5.80 \u00d7 10<sup>\u22126</sup> |\n|  | 120 \u00b0C | 6.02 \u00d7 10<sup>\u22127</sup> | 2.60 \u00d7 10<sup>\u22126</sup> | 6.85 \u00d7 10<sup>\u22126</sup> |\n|  | 140 \u00b0C | 1.04 \u00d7 10<sup>\u22126</sup> | 3.42 \u00d7 10<sup>\u22126</sup> | 7.82 \u00d7 10<sup>\u22126</sup> |\n| *E*<sub>A</sub> [eV] |  | 0.34 | 0.23 | 0.10 |", "data": [{"meta": {"name": "Ni-CAU-29", "symbol": "", "chemical formula": ""}, "conductivity": [{"temperature": "80 \u00b0C", "humidity": "50%rh", "value": "2.41 \u00d7 10^\u22127", "unit": "S cm^\u22121", "condition": ""}, {"temperature": "80 \u00b0C", "humidity": "75%rh", "value": "1.35 \u00d7 10^\u22126", "unit": "S cm^\u22121", "condition": ""}, {"temperature": "80 \u00b0C", "humidity": "90%rh", "value": "5.62 \u00d7 10^\u22126", "unit": "S cm^\u22121", "condition": ""}, {"temperature": "100 \u00b0C", "humidity": "50%rh", "value": "3.46 \u00d7 10^\u22127", "unit": "S cm^\u22121", "condition": ""}, {"temperature": "100 \u00b0C", "humidity": "75%rh", "value": "1.78 \u00d7 10^\u22126", "unit": "S cm^\u22121", "condition": ""}, {"temperature": "100 \u00b0C", "humidity": "90%rh", "value": "5.80 \u00d7 10^\u22126", "unit": "S cm^\u22121", "condition": ""}, {"temperature": "120 \u00b0C", "humidity": "50%rh", "value": "6.02 \u00d7 10^\u22127", "unit": "S cm^\u22121", "condition": ""}, {"temperature": "120 \u00b0C", "humidity": "75%rh", "value": "2.60 \u00d7 10^\u22126", "unit": "S cm^\u22121", "condition": ""}, {"temperature": "120 \u00b0C", "humidity": "90%rh", "value": "6.85 \u00d7 10^\u22126", "unit": "S cm^\u22121", "condition": ""}, {"temperature": "140 \u00b0C", "humidity": "50%rh", "value": "1.04 \u00d7 10^\u22126", "unit": "S cm^\u22121", "condition": ""}, {"temperature": "140 \u00b0C", "humidity": "75%rh", "value": "3.42 \u00d7 10^\u22126", "unit": "S cm^\u22121", "condition": ""}, {"temperature": "140 \u00b0C", "humidity": "90%rh", "value": "7.82 \u00d7 10^\u22126", "unit": "S cm^\u22121", "condition": ""}], "activation_energy": [{"value": "0.34", "unit": "eV", "condition": ""}, {"value": "0.23", "unit": "eV", "condition": ""}, {"value": "0.10", "unit": "eV", "condition": ""}]}], "include_properties": null}]